PyFHD/__git__.py
PyFHD/__init__.py
PyFHD/pyfhd.py
PyFHD/beam_setup/__init__.py
PyFHD/beam_setup/antenna.py
PyFHD/beam_setup/beam.py
PyFHD/beam_setup/beam_utils.py
PyFHD/beam_setup/mwa.py
PyFHD/calibration/__init__.py
PyFHD/calibration/calibrate.py
PyFHD/calibration/calibration_utils.py
PyFHD/calibration/vis_calibrate_subroutine.py
PyFHD/data_setup/__init__.py
PyFHD/data_setup/obs.py
PyFHD/data_setup/uvfits.py
PyFHD/flagging/__init__.py
PyFHD/flagging/flagging.py
PyFHD/gridding/__init__.py
PyFHD/gridding/filters.py
PyFHD/gridding/gridding_utils.py
PyFHD/gridding/visibility_degrid.py
PyFHD/gridding/visibility_grid.py
PyFHD/healpix/__init__.py
PyFHD/healpix/export.py
PyFHD/healpix/healpix_utils.py
PyFHD/io/__init__.py
PyFHD/io/pyfhd_io.py
PyFHD/io/pyfhd_quickview.py
PyFHD/plotting/__init__.py
PyFHD/plotting/calibration.py
PyFHD/plotting/gridding.py
PyFHD/plotting/image.py
PyFHD/pyfhd_tools/__init__.py
PyFHD/pyfhd_tools/pyfhd_setup.py
PyFHD/pyfhd_tools/pyfhd_utils.py
PyFHD/pyfhd_tools/test_utils.py
PyFHD/pyfhd_tools/unit_conv.py
PyFHD/resources/1088285600_example/1088285600.metafits
PyFHD/resources/1088285600_example/1088285600.uvfits
PyFHD/resources/1088285600_example/1088285600_example.yaml
PyFHD/resources/1088285600_example/1088285600_model.uvfits
PyFHD/resources/1088285600_example/gauss_beam_pointing0_167635008Hz.h5
PyFHD/resources/config/pyfhd.yaml
PyFHD/resources/healpix/EoR0_high_healpix_inds.h5
PyFHD/resources/healpix/EoR0_high_healpix_inds_3x.h5
PyFHD/resources/healpix/EoR0_high_healpix_inds_large.h5
PyFHD/resources/healpix/EoR0_low_healpix_inds.h5
PyFHD/resources/healpix/EoR1_high_healpix_inds.h5
PyFHD/resources/healpix/EoR1_low_healpix_inds.h5
PyFHD/resources/instrument_config/mwa_LNA_impedance.sav
PyFHD/resources/instrument_config/mwa_ZMatrix.fits
PyFHD/resources/instrument_config/mwa_cable_length.txt
PyFHD/resources/instrument_config/mwa_cable_reflection_coefficients.txt
PyFHD/resources/instrument_config/mwa_dead_dipole_list.txt
pyfhd-1.0.2.dist-info/METADATA
pyfhd-1.0.2.dist-info/WHEEL
pyfhd-1.0.2.dist-info/entry_points.txt
pyfhd-1.0.2.dist-info/licenses/LICENSE
pyfhd-1.0.2.dist-info/RECORD
