Metadata-Version: 2.4
Name: PyFHD
Version: 1.0.2
Summary: Python Fast Holograhic Deconvolution: A Python package that does fast-mode Epoch of Reionization analysis.
Project-URL: Repository, https://github.com/EoRImaging/PyFHD
Project-URL: Documentation, https://pyfhd.readthedocs.io/en/latest/
Project-URL: Bug Tracker, https://github.com/EoRImaging/PyFHD/issues
Project-URL: Changelog, https://pyfhd.readthedocs.io/en/latest/changelog/changelog.html
Author-email: "Joel Dunstan (SkyWa7ch3r)" <joel.g.w.dunstan@gmail.com>, "Jack Line (JLBLine)" <jack.line@curtin.edu.au>, "Nichole Barry (nicholebarry)" <nichole.barry@unsw.edu.au>
License: MIT License
License-File: LICENSE
Classifier: Development Status :: 4 - Beta
Classifier: Intended Audience :: Science/Research
Classifier: License :: OSI Approved :: MIT License
Classifier: Operating System :: OS Independent
Classifier: Programming Language :: Python :: 3
Classifier: Programming Language :: Python :: 3.10
Classifier: Programming Language :: Python :: 3.11
Classifier: Programming Language :: Python :: 3.12
Classifier: Programming Language :: Python :: 3.13
Classifier: Topic :: Scientific/Engineering :: Astronomy
Requires-Python: >=3.10
Requires-Dist: astropy>=6.1.7
Requires-Dist: colorama>=0.4.6
Requires-Dist: configargparse>=1.7
Requires-Dist: h5py>=3.13.0
Requires-Dist: healpy>=1.18.1
Requires-Dist: importlib-resources>=6.5.2
Requires-Dist: matplotlib>=3.10.3
Requires-Dist: numba>=0.61.2
Requires-Dist: numpy>=2.2.5
Requires-Dist: pyuvdata>=3.2.1
Requires-Dist: scipy>=1.15.3
